<transcript>
<page num="1">
<lettertext id="0502">
<folioref id="0412">
fol.6r
</folioref>
<newline/>
Honnorable S
<super id="0426" replace="ir">
r
</super>
,
<newline/>
wee her 
<person id="6511" person_id="Elizabeth">
majesties
</person>
 fore Captain[es]
<newline/>
yeat faythfull, and most loyall in o[ur]
<newline/>
place,
 wheare wee are Imployed, doe sa[.]
<newline/>
unto your Lor. w
<super id="0430" replace="ith">
th
</super>
 these, most humblye 
<newline/>
beseachinge you to taske suche notes
<newline/>
of a petition, the w
<super id="0433" replace="hich">
ch
</super>
 wee have writte[n]
<newline/>
to the 
<person id="6514" person_id="States General">
Stat
<image name="es"/>
,
</person>
 as you in your wisdom
<newline/>
shall finde best beseaming our honno[r]
<newline/>
and the Repeutation of our Nation.
<newline/>
<newline/>
Wee macke noe question, but that the
<newline/>
same shall cum unto your readinge, &amp;
<newline/>
theirfore will [mee], but brieflye to ad[.]
<newline/>
unto you, the Content
<image name="es"/>
 theirof.
<newline/>
wee are by sum divellishe &amp; moste
<newline/>
ungodlye persons, Charged to have
<newline/>
Intellygence, and to goe about to
<newline/>
betraye this towne unto the Enemy
<newline/>
yf the same maye not be prove[n]
<newline/>
wee knowe yt can not, then doe
<newline/>
earnestlye beseache you soe to
<newline/>
prosecute our accusors, as that
<newline/>
theire maye be the lycke punnish[ment]
<newline/>
Inflicted upon them, as should have
<newline/>
bein fitt for us, yf the same coul[d]
<newline/>
have bein founde trewe. The grea[t]
<newline/>
Charge from our Lord Governor, 
<newline/>
together w
<super id="0468" replace="ith">
th
</super>
 the assewered confyden[ce]
<newline/>
wee have that the Stat
<image name="es"/>
 will
<newline/>
dewlye consyder what wee are, &amp;
<newline/>
the nateuer of the accusation
<newline/>
dothe &amp; hathe w
<super id="0465" replace="ith">
th
</super>
 helde some of
<newline/>
<folioref id="0462">
fol.6v
</folioref>
 from satisfinge our selfes [.]
<newline/>
bloudd of them &amp; soe the s[.]
<newline/>
shall still cause us to pawse [.]
<newline/>
understand what will be d[.]
<newline/>
by them theire. and soe, as we[.]
<newline/>
Refer our selfes to your honno[rable]
<newline/>
care of us hearin, soe doe wee
<newline/>
beseache your Lordship to adv[.]
<newline/>
the delyverye of the sayed [.]
<newline/>
by the meanes of this [berer.]
<newline/>
<newline/>
<section id="0499" Section="subscription" Place="none">
your Lord shall finde us ever [.]
<newline/>
redie to doe you all the service [.]
<newline/>
wee can &amp; soe moste humblye
<newline/>
tacke our leaves from Ostend
<newline/>
5 Janeuarie. 1595.
<newline/>
Yo
<super id="0489" replace="ur">
r
</super>
 Lor. moste liu[.]
<newline/>
to Commaunde.
<newline/>
[Prob gachim]
<newline/>
Charles Brest
<newline/>
Thomas Farances
<newline/>
J Heochmacke
<newline/>
George Aldryche
<newline/>
Water F[.]
<newline/>
Richard Su[.]
</section>
</lettertext>
</page>
</transcript>
