<transcript>
<page num="1">
<lettertext id="0099">
<folioref id="0002">
fol.24r
</folioref>
 
<missing id="0005" type="fire">
After
</missing>
 our hartie commendacions: Her m
<overline id="0008" replace="ajes">
a
</overline>
tie doth nowe
<newline/>
Returne 
<person id="0091" person_id="Vere, F">
S
<super id="0012" replace="ir">
r
</super>
 Francis Veare
</person>
, whose lycence to come over, yo
<super id="0015" replace="">
w
</super>
<newline/>
procured of The States by her m
<overline id="0022" replace="ayjes">
ay
</overline>
ties Commandem
<super id="0081" replace="ent">
t
</super>
. It hath
<newline/>
pleased her also to referre to his Reporte, the credytt of all
<newline/>
such particulers as he shall deale in, being not fytt to be
<newline/>
committed to Paper, and by her owne l
<overline id="0084" replace="ettre">
re
</overline>
s, wherof wee send yo
<super id="0028" replace="">
w
</super>
 a
<newline/>
coppie to warrant what he shall propownde: Herein as in all
<newline/>
other thinges, because her maytie is well pleased to use yo
<super id="0087" replace="ur">
r
</super>
 service
<newline/>
as the propre Instrument of her adresses to that States, and of
<newline/>
whose wisdome and seccrecie in her causes shee hath so many
<newline/>
good argument
<image name="es"/>
. Her may
<abbreviation id="0085" replace="jestie">
tie
</abbreviation>
 hath commanded us in her name
<newline/>
to require yo
<super id="0038" replace="">
w
</super>
, after he shall have acquainted yo
<super id="0041" replace="">
w
</super>
, w
<super id="0090" replace="ith">
th
</super>
all the
<newline/>
circumstances, both to yeld him yo
<super id="0093" replace="ur">
r
</super>
 advise in what sorte best
<newline/>
to propownde her desire, and also seryouselie to labour 
<image name="thorn"/>
e expedicion
<newline/>
of 
<image name="thorn"/>
e same as a matter importing her service greatly, and wherin
<newline/>
nothing is of greater consequence then the advantage of tyme
<newline/>
well gayned; and thus referring the rest to 
<image name="thorn"/>
e gen
<abbreviation id="0052" replace="tleman's">
t:
</abbreviation>
 owne
<newline/>
Intimation, wee commytt yo
<super id="0056" replace="">
w
</super>
 to God. 
<section id="0096" Section="subscription" Place="none">
From 
<image name="thorn"/>
e Corte at
<newline/>
<highlight id="0061" Type="italic">
Richmonde
</highlight>
 the xviij
<super id="0105" replace="">
th
</super>
 of 
<underline id="0070">
Fe
<abbreviation id="0067" replace="bruarie">
b:
</abbreviation>
 1595
</underline>
<newline/>
Yo
<super id="0074" replace="ur">
r
</super>
 very Loving friend
<image name="es"/>
 
<person id="0095" person_id="Burghley">
William Burghley
</person>
<newline/>
<person id="0100" person_id="Devereux, R">
Essex
</person>
<newline/>
<person id="0103" person_id="Howard, C">
Charles Howard
</person>
<newline/>
<person id="0106" person_id="Cecil, R">
Robert Cecyll
</person>
</section>
</lettertext>
</page>
</transcript>
